aqueduct/__init__.py
aqueduct/exceptions.py
aqueduct/flow.py
aqueduct/handler.py
aqueduct/logger.py
aqueduct/multiprocessing.py
aqueduct/queues.py
aqueduct/task.py
aqueduct/utils.py
aqueduct/worker.py
aqueduct/integrations/__init__.py
aqueduct/integrations/aiohttp.py
aqueduct/integrations/zero.py
aqueduct/metrics/__init__.py
aqueduct/metrics/base.py
aqueduct/metrics/collect.py
aqueduct/metrics/export.py
aqueduct/metrics/manager.py
aqueduct/metrics/processes.py
aqueduct/metrics/queue.py
aqueduct/metrics/task.py
aqueduct/metrics/timer.py
aqueduct/shm/__init__.py
aqueduct/shm/_atomic.abi3.so
aqueduct/shm/base.py
aqueduct/shm/bytes.py
aqueduct/shm/mixin.py
aqueduct/shm/numpy.py
aqueduct/sockets/__init__.py
aqueduct/sockets/connection_pool.py
aqueduct/sockets/flow.py
aqueduct/sockets/flow_server.py
aqueduct/sockets/protocol.py
tests/__init__.py
tests/conftest.py
tests/benchmarks/__init__.py
tests/benchmarks/bench_queue_transfer.py
tests/benchmarks/utils.py
tests/benchmarks/bench_service/__init__.py
tests/benchmarks/bench_service/bench/__init__.py
tests/benchmarks/bench_service/bench/base.py
tests/benchmarks/bench_service/bench/bench_configurations.py
tests/benchmarks/bench_service/bench/bench_steps.py
tests/benchmarks/bench_service/bench/rps_counter.py
tests/benchmarks/bench_service/bench/utils.py
tests/unit/__init__.py
tests/unit/conftest.py
tests/unit/test_flow.py
tests/unit/test_shm.py
tests/unit/test_sockets.py
tests/unit/test_task.py
tests/unit/test_worker.py
tests/unit/integrations/__init__.py
tests/unit/integrations/test_aiohttp.py
tests/unit/metrics/__init__.py
tests/unit/metrics/test_collect.py
tests/unit/metrics/test_export.py
tests/unit/metrics/test_metrics.py
tests/unit/metrics/test_task.py
aqueduct-1.13.0.dist-info/METADATA
aqueduct-1.13.0.dist-info/WHEEL
aqueduct-1.13.0.dist-info/top_level.txt
aqueduct-1.13.0.dist-info/RECORD
