Metadata-Version: 2.4
Name: aqueduct
Version: 1.13.0
Summary: Builder for performance-efficient prediction.
Home-page: https://github.com/avito-tech/aqueduct
Download-URL: https://github.com/avito-tech/aqueduct/archive/refs/heads/main.zip
Author: Data Science SWAT
Author-email: UnitDataScienceSwat@avito.ru
License: MIT
Keywords: datascience,learning
Classifier: Development Status :: 4 - Beta
Classifier: Intended Audience :: Developers
Classifier: Topic :: Scientific/Engineering
Classifier: Topic :: Software Development :: Build Tools
Classifier: Topic :: Software Development :: Libraries :: Python Modules
Classifier: Topic :: Software Development :: Libraries :: Python Modules
Classifier: License :: OSI Approved :: MIT License
Classifier: Programming Language :: Python :: 3.8
Classifier: Operating System :: MacOS
Classifier: Operating System :: Microsoft :: Windows
Classifier: Operating System :: POSIX
Classifier: Operating System :: Unix
Classifier: Operating System :: OS Independent
Requires-Python: >=3.8
Requires-Dist: psutil==5.9.4
Provides-Extra: aiohttp
Requires-Dist: aiohttp; extra == "aiohttp"
Provides-Extra: numpy
Requires-Dist: numpy; extra == "numpy"
Dynamic: author
Dynamic: author-email
Dynamic: classifier
Dynamic: description
Dynamic: description-content-type
Dynamic: download-url
Dynamic: home-page
Dynamic: keywords
Dynamic: license
Dynamic: provides-extra
Dynamic: requires-dist
Dynamic: requires-python
Dynamic: summary
